LICENSE.md
README.md
setup.cfg
setup.py
MacroQueue/Dialogs.py
MacroQueue/GUIDesign.py
MacroQueue/MacroQueue.py
MacroQueue/MacroQueueIcon.ico
MacroQueue/MakeExe.sh
MacroQueue/__init__.py
MacroQueue/__main__.py
MacroQueue.egg-info/PKG-INFO
MacroQueue.egg-info/SOURCES.txt
MacroQueue.egg-info/dependency_links.txt
MacroQueue.egg-info/requires.txt
MacroQueue.egg-info/top_level.txt
MacroQueue/Bitmaps/DownArrow.bmp
MacroQueue/Bitmaps/Remove.bmp
MacroQueue/Bitmaps/UpArrow.bmp
MacroQueue/Functions/BField.py
MacroQueue/Functions/CreaTec.py
MacroQueue/Functions/Example.py
MacroQueue/Functions/General.py
MacroQueue/Functions/RF.py
MacroQueue/Functions/RHK.py
MacroQueue/Functions/SXM.py
MacroQueue/Functions/SXMRemote.py
MacroQueue/Functions/Testing.py
MacroQueue/Macros/CreaTecMacro.json
MacroQueue/Macros/RHKMacro.json
MacroQueue/Macros/TestingMacro.json
test/test_MainFrame.py
test/test_STMthread.py
test/test_readdata.py