Metadata-Version: 2.1
Name: MacroQueue
Version: 0.4.3
Summary: Automating Scanning Probe Microscopy
Home-page: https://github.com/guptagroupstm/STMMacroQueue
Download-URL: https://github.com/guptagroupstm/STMMacroQueue/archive/refs/tags/v0.4.3.tar.gz
Author: Brad Goff
Author-email: guptagroupstm@gmail.com
License: MIT
Keywords: Automation,Scanning Probe Microscopy,Macro,Queue
Classifier: Development Status :: 4 - Beta
Classifier: Intended Audience :: Science/Research
Classifier: Topic :: Scientific/Engineering :: Physics
Classifier: License :: OSI Approved :: MIT License
Classifier: Programming Language :: Python :: 3
Classifier: Programming Language :: Python :: 3.9
License-File: LICENSE.md
Requires-Dist: pandas
Requires-Dist: wxPython
Requires-Dist: pyvisa
Requires-Dist: pyinstaller
Requires-Dist: importlib_metadata
Requires-Dist: numpy
